okrequest/__init__.py
okrequest/api.py
okrequest/exceptions.py
okrequest/models.py
okrequest/sessions.py
okrequest/libs/httpclient.dll
okrequest/libs/httpclient.h
okrequest/libs/httpclient.so
okrequest-0.0.7.dist-info/METADATA
okrequest-0.0.7.dist-info/WHEEL
okrequest-0.0.7.dist-info/top_level.txt
okrequest-0.0.7.dist-info/RECORD
