Metadata-Version: 2.2
Name: okrequest
Version: 0.0.7
Summary: 一个类似 requests 的 HTTP 客户端库
Home-page: 
Author: 
Author-email: 
Classifier: Programming Language :: Python :: 3
Classifier: License :: OSI Approved :: MIT License
Classifier: Operating System :: OS Independent
Requires-Python: >=3.6
Dynamic: classifier
Dynamic: description
Dynamic: description-content-type
Dynamic: requires-python
Dynamic: summary
